python_everhour/__init__.py
python_everhour/api.py
python_everhour/config/prod.yaml
python_everhour/config/test.yaml
python_everhour-0.1.1.dist-info/METADATA
python_everhour-0.1.1.dist-info/WHEEL
python_everhour-0.1.1.dist-info/licenses/LICENSE.txt
python_everhour-0.1.1.dist-info/RECORD
