Metadata-Version: 2.3
Name: python-everhour
Version: 0.1.1
Summary: Add your description here
License-File: LICENSE.txt
Requires-Python: >=3.10
Requires-Dist: pyyaml>=6.0.2
Requires-Dist: requests>=2.32.3
